lab3/phase_1_design_compiler/src/GCD.vhdl
----------------------------------------------------------------------
-- GCD CALCULATOR 
-- RT level modeling (FSM + DataPath)
----------------------------------------------------------------------

-- Component: MULTIPLEXOR --------------------------------------------

library IEEE;
use IEEE.std_logic_1164.all;
use IEEE.std_logic_arith.all;
use IEEE.std_logic_unsigned.all;

entity mux is 
    port(	rst, sLine: in std_logic;
		load, result: in std_logic_vector( 3 downto 0 );
		output: out std_logic_vector( 3 downto 0 )
    );
end mux;

architecture mux_arc of mux is
begin
    process( rst, sLine, load, result )
    begin
	if( rst = '1' ) then 
	    output <= "0000";		-- do nothing
	elsif sLine = '0' then 
	    output <= load;		-- load inputs
	else 
	    output <= result;		-- load results
	end if;
    end process;
end mux_arc;
	
-- Component: COMPARATOR ---------------------------------------------

library IEEE;
use IEEE.std_logic_1164.all;
use IEEE.std_logic_arith.all;
use IEEE.std_logic_unsigned.all;

entity comparator is
    port(	rst: in std_logic;
		x, y: in std_logic_vector( 3 downto 0 );
		output: out std_logic_vector( 1 downto 0 )
    );
end comparator;

architecture comparator_arc of comparator is
begin
    process( x, y, rst )
    begin
	if( rst = '1' ) then 
	    output <= "00";		-- do nothing
	elsif( x > y ) then 
	    output <= "10";		-- if x greater
	elsif( x < y ) then 
	    output <= "01";		-- if y greater
	else 
	    output <= "11";  	        -- if equivalance. 	
	end if;
    end process;
end comparator_arc;

-- Component: SUBTRACTOR ----------------------------------------------

library IEEE;
use IEEE.std_logic_1164.all;
use IEEE.std_logic_arith.all;
use IEEE.std_logic_unsigned.all;

entity subtractor is
    port(	rst: in std_logic;
		cmd: in std_logic_vector( 1 downto 0 );
		x, y: in std_logic_vector( 3 downto 0 );
		xout, yout: out std_logic_vector( 3 downto 0 )
    );
end subtractor;

architecture subtractor_arc of subtractor is
begin
    process( rst, cmd, x, y )
    begin
	if( rst = '1' or cmd = "00" ) then 	-- not active.
	    xout <= "0000";	
	    yout <= "0000";
	elsif( cmd = "10" ) then 		-- x is greater
	    xout <= ( x - y );
	    yout <= y;
	elsif( cmd = "01" ) then 		-- y is greater
	    xout <= x;	
	    yout <= ( y - x );
	else 
	    xout <= x;  			-- x and y are equal
	    yout <= y; 		
	end if;
    end process;
end subtractor_arc;

-- Component: REGISTER ---------------------------------------------------

library IEEE;
use IEEE.std_logic_1164.all;
use IEEE.std_logic_arith.all;
use IEEE.std_logic_unsigned.all;

entity regis is
    port(	rst, clk, load: in std_logic;
	        input: in std_logic_vector( 3 downto 0 );
		output: out std_logic_vector( 3 downto 0 )
    );
end regis;

architecture regis_arc of regis is
begin
    process( rst, clk, load, input )
    begin
	if( rst = '1' ) then 
	    output <= "0000";
	elsif( clk'event and clk = '1') then
	    if( load = '1' ) then	
	        output <= input;
	    end if;
        end if;
    end process;
end regis_arc;

-- component: FSM controller --------------------------------------------

library IEEE;
use IEEE.std_logic_1164.all;
use IEEE.std_logic_arith.all;
use IEEE.std_logic_unsigned.all;

entity fsm is
    port(	rst, clk, proceed: in std_logic;
		comparison: in std_logic_vector( 1 downto 0 );
		enable, xsel, ysel, xld, yld: out std_logic
    );
end fsm;

architecture fsm_arc of fsm is

    type states is ( init, s0, s1, s2, s3, s4, s5 );
    signal nState, cState: states;

begin
    process( rst, clk )
    begin
	if( rst = '1' ) then 
	    cState <= init;
	elsif( clk'event and clk = '1' ) then 
	    cState <= nState;
	end if;
    end process;

    process( proceed, comparison, cState )
    begin

	case cState is 
		
	when init =>	
            if( proceed = '0' ) then 
			    nState <= init;
			else 
			    nState <= s0;
			end if;
            enable <= '0';
            xsel <= '0';
            ysel <= '0';
            xld <= '0';
            yld <= '0';

	when s0 =>	
			nState <= s1;
            enable <= '0';
			xsel <= '0';
			ysel <= '0';
			xld <= '0';
			yld <= '0';
	
	when s1 =>	
			nState <= s2;
            enable <= '0';
			xsel <= '0';
			ysel <= '0';
			xld <= '1';
			yld <= '1';
		
	when s2 =>	
            if( comparison = "10" ) then 
			    nState <= s3;
			elsif( comparison = "01" ) then 
			    nState <= s4; 	
			elsif( comparison = "11" ) then 
			    nState <= s5;   
            else 
                nState <= s2;	
			end if;
            enable <= '0';
            xsel <= '0';
            ysel <= '0';
            xld <= '0';
            yld <= '0';
		
	when s3 =>	
            nState <= s2;
            enable <= '0';
			xsel <= '1';
			ysel <= '0';
			xld <= '1';
			yld <= '0';
	
	when s4 =>	
			nState <= s2;
            enable <= '0';
			xsel <= '0';
			ysel <= '1';
			xld <= '0';
			yld <= '1';

	when s5 =>	
            nState <= s0;
            enable <= '1';
			xsel <= '1';
			ysel <= '1';
			xld <= '1';
			yld <= '1';
			
	when others =>	
            nState <= s0;
            enable <= '0';
            xsel <= '0';
            ysel <= '0';
            xld <= '0';
            yld <= '0';
			
    end case;
	
    end process;
	
end fsm_arc;

----------------------------------------------------------------------
-- GCD Calculator: top level design using structural modeling
-- FSM + Datapath (mux, registers, subtracter and comparator)
----------------------------------------------------------------------

library IEEE;
use IEEE.std_logic_1164.all;
use IEEE.std_logic_arith.all;
use IEEE.std_logic_unsigned.all;
use work.all;

entity gcd is
    port(	rst, clk, go_i: in std_logic;
--    		my_tdi, my_tms, my_tck, my_trst: in std_logic;
--    		my_tdo: out std_logic;
		x_i, y_i: in std_logic_vector( 3 downto 0 );
		d_o: out std_logic_vector( 3 downto 0 )
    );
end gcd;

architecture gcd_arc of gcd is

component fsm is
    port(	rst, clk, proceed: in std_logic;
		comparison: in std_logic_vector( 1 downto 0 );
		enable, xsel, ysel, xld, yld: out std_logic
    );
end component;

component mux is 
    port(	rst, sLine: in std_logic;
		load, result: in std_logic_vector( 3 downto 0 );
		output: out std_logic_vector( 3 downto 0 )
    );
end component;

component comparator is
    port(	rst: in std_logic;
		x, y: in std_logic_vector( 3 downto 0 );
		output: out std_logic_vector( 1 downto 0 )
    );
end component;

component subtractor is
    port( 	rst: in std_logic; 
		cmd: in std_logic_vector( 1 downto 0 );
		x, y: in std_logic_vector( 3 downto 0 );
		xout, yout: out std_logic_vector( 3 downto 0 )
    );
end component;

component regis is
    port(	rst, clk, load: in std_logic;
		input: in std_logic_vector( 3 downto 0 );
		output: out std_logic_vector( 3 downto 0 )
    );
end component;

signal xld, yld, xsel, ysel, enable: std_logic;
signal comparison: std_logic_vector( 1 downto 0 );
signal result: std_logic_vector( 3 downto 0 );					

signal xsub, ysub, xmux, ymux, xreg, yreg: std_logic_vector( 3 downto 0 );

begin

    -- doing structure modeling here

    -- FSM controller
    TOFSM: fsm port map(    rst, clk, go_i, comparison, 
			    enable, xsel, ysel, xld, yld );   				 
    -- Datapath
    X_MUX: mux port map( rst, xsel, x_i, xsub, xmux );
    Y_MUX: mux port map( rst, ysel, y_i, ysub, ymux );
    X_REG: regis port map( rst, clk, xld, xmux, xreg ); 
    Y_REG: regis port map( rst, clk, yld, ymux, yreg ); 
    U_COMP: comparator port map( rst, xreg, yreg, comparison );
    X_SUB: subtractor port map( rst, comparison, xreg, yreg, xsub, ysub );
    OUT_REG: regis port map( rst, clk, enable, xsub, result );
	
    d_o <= result; 

end gcd_arc;

lab3/source_design/gcd_tb.v
`timescale 1ns/1ps
module gcd_tb();
    reg rst, clk, go_i;
    reg[3:0] x_i, y_i;
    wire[3:0] d_o;

    gcd uut(.rst(rst), .clk(clk), .go_i(go_i), .x_i(x_i), .y_i(y_i), .d_o(d_o));

    parameter period = 40;
    parameter cycles_per_test = 30;
    
    task TestGCD;
        input [3:0] xValue, yValue; 
        input integer correct_result;
        begin
            x_i = xValue;
            y_i = yValue;
            go_i = 1;
            #(period);
            go_i = 0;
            #(cycles_per_test * period);
            if (d_o != correct_result) begin
                $display("Test failed for gcd(%d,%d) = %0d",  xValue, yValue, correct_result);
                $display("%d", $time);
            end
        end
    endtask

    initial begin
        clk = 0;
    end

    always #(period/2) clk = ~clk;

    always @(negedge clk) begin
        // Initialize
        rst = 1;
        go_i = 0;
        x_i = 0;
        y_i = 0;
        #(period);
        rst = 0;
        #(period);

        $display("\nStarting Tests:");
        TestGCD(12, 8, 4);
        TestGCD(14, 7, 7);
        TestGCD(15, 13, 1);
        TestGCD(11, 3, 1);
        TestGCD(5, 15, 5);
        TestGCD(6, 6, 6);
        TestGCD(8, 7, 1);
        TestGCD(15, 2, 1);

        $display("Simulation Complete");
        $stop;
        
    end

endmodule

lab3/phase_1_generate_RTL_SAIF/gcd_rtl.vcd
$date
	Thu Apr 15 20:08:55 2021
$end
$version
	ModelSim Version 10.6c
$end
$timescale
	1ps
$end

$scope module gcd_tb $end
$var parameter 32 ! period $end
$var parameter 32 " cycles_per_test $end
$var reg 1 # rst $end
$var reg 1 $ clk $end
$var reg 1 % go_i $end
$var reg 4 & x_i [3:0] $end
$var reg 4 ' y_i [3:0] $end
$var wire 1 ( d_o [3] $end
$var wire 1 ) d_o [2] $end
$var wire 1 * d_o [1] $end
$var wire 1 + d_o [0] $end
$upscope $end
$enddefinitions $end
#0
$dumpvars
1#
0$
0%
b0 &
b0 '
b101000 !
b11110 "
0+
0*
0)
0(
$end
#20000
1$
#40000
0#
0$
#60000
1$
#80000
b1100 &
b1000 '
1%
0$
#100000
1$
#120000
0%
0$
#140000
1$
#160000
0$
#180000
1$
#200000
0$
#220000
1$
#240000
0$
#260000
1$
#280000
0$
#300000
1$
#320000
0$
#340000
1$
#360000
0$
#380000
1$
#400000
0$
#420000
1$
1)
#440000
0$
#460000
1$
#480000
0$
#500000
1$
#520000
0$
#540000
1$
#560000
0$
#580000
1$
#600000
0$
#620000
1$
#640000
0$
#660000
1$
#680000
0$
#700000
1$
#720000
0$
#740000
1$
#760000
0$
#780000
1$
#800000
0$
#820000
1$
#840000
0$
#860000
1$
#880000
0$
#900000
1$
#920000
0$
#940000
1$
#960000
0$
#980000
1$
#1000000
0$
#1020000
1$
#1040000
0$
#1060000
1$
#1080000
0$
#1100000
1$
#1120000
0$
#1140000
1$
#1160000
0$
#1180000
1$
#1200000
0$
#1220000
1$
#1240000
0$
#1260000
1$
#1280000
0$
#1300000
1$
#1320000
b1110 &
b111 '
1%
0$
#1340000
1$
#1360000
0%
0$
#1380000
1$
#1400000
0$
#1420000
1$
#1440000
0$
#1460000
1$
#1480000
0$
#1500000
1$
#1520000
0$
#1540000
1$
#1560000
0$
#1580000
1$
#1600000
0$
#1620000
1$
1+
1*
