lab3/phase_1_design_compiler/src/GCD.vhdl
----------------------------------------------------------------------
-- GCD CALCULATOR 
-- RT level modeling (FSM + DataPath)
----------------------------------------------------------------------

-- Component: MULTIPLEXOR --------------------------------------------

library IEEE;
use IEEE.std_logic_1164.all;
use IEEE.std_logic_arith.all;
use IEEE.std_logic_unsigned.all;

entity mux is 
    port(	rst, sLine: in std_logic;
		load, result: in std_logic_vector( 3 downto 0 );
		output: out std_logic_vector( 3 downto 0 )
    );
end mux;

architecture mux_arc of mux is
begin
    process( rst, sLine, load, result )
    begin
	if( rst = '1' ) then 
	    output <= "0000";		-- do nothing
	elsif sLine = '0' then 
	    output <= load;		-- load inputs
	else 
	    output <= result;		-- load results
	end if;
    end process;
end mux_arc;
	
-- Component: COMPARATOR ---------------------------------------------

library IEEE;
use IEEE.std_logic_1164.all;
use IEEE.std_logic_arith.all;
use IEEE.std_logic_unsigned.all;

entity comparator is
    port(	rst: in std_logic;
		x, y: in std_logic_vector( 3 downto 0 );
		output: out std_logic_vector( 1 downto 0 )
    );
end comparator;

architecture comparator_arc of comparator is
begin
    process( x, y, rst )
    begin
	if( rst = '1' ) then 
	    output <= "00";		-- do nothing
	elsif( x > y ) then 
	    output <= "10";		-- if x greater
	elsif( x < y ) then 
	    output <= "01";		-- if y greater
	else 
	    output <= "11";  	        -- if equivalance. 	
	end if;
    end process;
end comparator_arc;

-- Component: SUBTRACTOR ----------------------------------------------

library IEEE;
use IEEE.std_logic_1164.all;
use IEEE.std_logic_arith.all;
use IEEE.std_logic_unsigned.all;

entity subtractor is
    port(	rst: in std_logic;
		cmd: in std_logic_vector( 1 downto 0 );
		x, y: in std_logic_vector( 3 downto 0 );
		xout, yout: out std_logic_vector( 3 downto 0 )
    );
end subtractor;

architecture subtractor_arc of subtractor is
begin
    process( rst, cmd, x, y )
    begin
	if( rst = '1' or cmd = "00" ) then 	-- not active.
	    xout <= "0000";	
	    yout <= "0000";
	elsif( cmd = "10" ) then 		-- x is greater
	    xout <= ( x - y );
	    yout <= y;
	elsif( cmd = "01" ) then 		-- y is greater
	    xout <= x;	
	    yout <= ( y - x );
	else 
	    xout <= x;  			-- x and y are equal
	    yout <= y; 		
	end if;
    end process;
end subtractor_arc;

-- Component: REGISTER ---------------------------------------------------

library IEEE;
use IEEE.std_logic_1164.all;
use IEEE.std_logic_arith.all;
use IEEE.std_logic_unsigned.all;

entity regis is
    port(	rst, clk, load: in std_logic;
	        input: in std_logic_vector( 3 downto 0 );
		output: out std_logic_vector( 3 downto 0 )
    );
end regis;

architecture regis_arc of regis is
begin
    process( rst, clk, load, input )
    begin
	if( rst = '1' ) then 
	    output <= "0000";
	elsif( clk'event and clk = '1') then
	    if( load = '1' ) then	
	        output <= input;
	    end if;
        end if;
    end process;
end regis_arc;

-- component: FSM controller --------------------------------------------

library IEEE;
use IEEE.std_logic_1164.all;
use IEEE.std_logic_arith.all;
use IEEE.std_logic_unsigned.all;

entity fsm is
    port(	rst, clk, proceed: in std_logic;
		comparison: in std_logic_vector( 1 downto 0 );
		enable, xsel, ysel, xld, yld: out std_logic
    );
end fsm;

architecture fsm_arc of fsm is

    type states is ( init, s0, s1, s2, s3, s4, s5 );
    signal nState, cState: states;

begin
    process( rst, clk )
    begin
	if( rst = '1' ) then 
	    cState <= init;
	elsif( clk'event and clk = '1' ) then 
	    cState <= nState;
	end if;
    end process;

    process( proceed, comparison, cState )
    begin

	case cState is 
		
	when init =>	
            if( proceed = '0' ) then 
			    nState <= init;
			else 
			    nState <= s0;
			end if;
            enable <= '0';
            xsel <= '0';
            ysel <= '0';
            xld <= '0';
            yld <= '0';

	when s0 =>	
			nState <= s1;
            enable <= '0';
			xsel <= '0';
			ysel <= '0';
			xld <= '0';
			yld <= '0';
	
	when s1 =>	
			nState <= s2;
            enable <= '0';
			xsel <= '0';
			ysel <= '0';
			xld <= '1';
			yld <= '1';
		
	when s2 =>	
            if( comparison = "10" ) then 
			    nState <= s3;
			elsif( comparison = "01" ) then 
			    nState <= s4; 	
			elsif( comparison = "11" ) then 
			    nState <= s5;   
            else 
                nState <= s2;	
			end if;
            enable <= '0';
            xsel <= '0';
            ysel <= '0';
            xld <= '0';
            yld <= '0';
		
	when s3 =>	
            nState <= s2;
            enable <= '0';
			xsel <= '1';
			ysel <= '0';
			xld <= '1';
			yld <= '0';
	
	when s4 =>	
			nState <= s2;
            enable <= '0';
			xsel <= '0';
			ysel <= '1';
			xld <= '0';
			yld <= '1';

	when s5 =>	
            nState <= s0;
            enable <= '1';
			xsel <= '1';
			ysel <= '1';
			xld <= '1';
			yld <= '1';
			
	when others =>	
            nState <= s0;
            enable <= '0';
            xsel <= '0';
            ysel <= '0';
            xld <= '0';
            yld <= '0';
			
    end case;
	
    end process;
	
end fsm_arc;

----------------------------------------------------------------------
-- GCD Calculator: top level design using structural modeling
-- FSM + Datapath (mux, registers, subtracter and comparator)
----------------------------------------------------------------------

library IEEE;
use IEEE.std_logic_1164.all;
use IEEE.std_logic_arith.all;
use IEEE.std_logic_unsigned.all;
use work.all;

entity gcd is
    port(	rst, clk, go_i: in std_logic;
--    		my_tdi, my_tms, my_tck, my_trst: in std_logic;
--    		my_tdo: out std_logic;
		x_i, y_i: in std_logic_vector( 3 downto 0 );
		d_o: out std_logic_vector( 3 downto 0 )
    );
end gcd;

architecture gcd_arc of gcd is

component fsm is
    port(	rst, clk, proceed: in std_logic;
		comparison: in std_logic_vector( 1 downto 0 );
		enable, xsel, ysel, xld, yld: out std_logic
    );
end component;

component mux is 
    port(	rst, sLine: in std_logic;
		load, result: in std_logic_vector( 3 downto 0 );
		output: out std_logic_vector( 3 downto 0 )
    );
end component;

component comparator is
    port(	rst: in std_logic;
		x, y: in std_logic_vector( 3 downto 0 );
		output: out std_logic_vector( 1 downto 0 )
    );
end component;

component subtractor is
    port( 	rst: in std_logic; 
		cmd: in std_logic_vector( 1 downto 0 );
		x, y: in std_logic_vector( 3 downto 0 );
		xout, yout: out std_logic_vector( 3 downto 0 )
    );
end component;

component regis is
    port(	rst, clk, load: in std_logic;
		input: in std_logic_vector( 3 downto 0 );
		output: out std_logic_vector( 3 downto 0 )
    );
end component;

signal xld, yld, xsel, ysel, enable: std_logic;
signal comparison: std_logic_vector( 1 downto 0 );
signal result: std_logic_vector( 3 downto 0 );					

signal xsub, ysub, xmux, ymux, xreg, yreg: std_logic_vector( 3 downto 0 );

begin

    -- doing structure modeling here

    -- FSM controller
    TOFSM: fsm port map(    rst, clk, go_i, comparison, 
			    enable, xsel, ysel, xld, yld );   				 
    -- Datapath
    X_MUX: mux port map( rst, xsel, x_i, xsub, xmux );
    Y_MUX: mux port map( rst, ysel, y_i, ysub, ymux );
    X_REG: regis port map( rst, clk, xld, xmux, xreg ); 
    Y_REG: regis port map( rst, clk, yld, ymux, yreg ); 
    U_COMP: comparator port map( rst, xreg, yreg, comparison );
    X_SUB: subtractor port map( rst, comparison, xreg, yreg, xsub, ysub );
    OUT_REG: regis port map( rst, clk, enable, xsub, result );
	
    d_o <= result; 

end gcd_arc;

lab3/source_design/gcd_tb.v
`timescale 1ns/1ps
module gcd_tb();
    reg rst, clk, go_i;
    reg[3:0] x_i, y_i;
    wire[3:0] d_o;

    gcd uut(.rst(rst), .clk(clk), .go_i(go_i), .x_i(x_i), .y_i(y_i), .d_o(d_o));

    parameter period = 40;
    parameter cycles_per_test = 30;
    
    task TestGCD;
        input [3:0] xValue, yValue; 
        input integer correct_result;
        begin
            x_i = xValue;
            y_i = yValue;
            go_i = 1;
            #(period);
            go_i = 0;
            #(cycles_per_test * period);
            if (d_o != correct_result) begin
                $display("Test failed for gcd(%d,%d) = %0d",  xValue, yValue, correct_result);
                $display("%d", $time);
            end
        end
    endtask

    initial begin
        clk = 0;
    end

    always #(period/2) clk = ~clk;

    always @(negedge clk) begin
        // Initialize
        rst = 1;
        go_i = 0;
        x_i = 0;
        y_i = 0;
        #(period);
        rst = 0;
        #(period);

        $display("\nStarting Tests:");
        TestGCD(12, 8, 4);
        TestGCD(14, 7, 7);
        TestGCD(15, 13, 1);
        TestGCD(11, 3, 1);
        TestGCD(5, 15, 5);
        TestGCD(6, 6, 6);
        TestGCD(8, 7, 1);
        TestGCD(15, 2, 1);

        $display("Simulation Complete");
        $stop;
        
    end

endmodule

lab3/phase_1_generate_RTL_SAIF/gcd_rtl.vcd
$date
	Thu Apr 15 23:12:21 2021
$end
$version
	ModelSim Version 10.6c
$end
$timescale
	1ps
$end

$scope module gcd_tb $end

$scope module uut $end
$var wire 1 ! rst $end
$var wire 1 " clk $end
$var wire 1 # go_i $end
$var wire 1 $ x_i [3] $end
$var wire 1 % x_i [2] $end
$var wire 1 & x_i [1] $end
$var wire 1 ' x_i [0] $end
$var wire 1 ( y_i [3] $end
$var wire 1 ) y_i [2] $end
$var wire 1 * y_i [1] $end
$var wire 1 + y_i [0] $end
$var wire 1 , d_o [3] $end
$var wire 1 - d_o [2] $end
$var wire 1 . d_o [1] $end
$var wire 1 / d_o [0] $end
$var wire 1 0 xld $end
$var wire 1 1 yld $end
$var wire 1 2 xsel $end
$var wire 1 3 ysel $end
$var wire 1 4 enable $end
$var wire 1 5 comparison [1] $end
$var wire 1 6 comparison [0] $end
$var wire 1 7 result [3] $end
$var wire 1 8 result [2] $end
$var wire 1 9 result [1] $end
$var wire 1 : result [0] $end
$var wire 1 ; xsub [3] $end
$var wire 1 < xsub [2] $end
$var wire 1 = xsub [1] $end
$var wire 1 > xsub [0] $end
$var wire 1 ? ysub [3] $end
$var wire 1 @ ysub [2] $end
$var wire 1 A ysub [1] $end
$var wire 1 B ysub [0] $end
$var wire 1 C xmux [3] $end
$var wire 1 D xmux [2] $end
$var wire 1 E xmux [1] $end
$var wire 1 F xmux [0] $end
$var wire 1 G ymux [3] $end
$var wire 1 H ymux [2] $end
$var wire 1 I ymux [1] $end
$var wire 1 J ymux [0] $end
$var wire 1 K xreg [3] $end
$var wire 1 L xreg [2] $end
$var wire 1 M xreg [1] $end
$var wire 1 N xreg [0] $end
$var wire 1 O yreg [3] $end
$var wire 1 P yreg [2] $end
$var wire 1 Q yreg [1] $end
$var wire 1 R yreg [0] $end
$upscope $end
$upscope $end
$enddefinitions $end
#0
$dumpvars
1!
0"
0#
00
01
02
03
04
0$
0%
0&
0'
0(
0)
0*
0+
0,
0-
0.
0/
05
06
07
08
09
0:
0;
0<
0=
0>
0?
0@
0A
0B
0C
0D
0E
0F
0G
0H
0I
0J
0K
0L
0M
0N
0O
0P
0Q
0R
$end
#20000
1"
#40000
0!
0"
16
15
#60000
1"
#80000
1(
1%
1$
1#
0"
1G
1D
1C
#100000
1"
#120000
0#
0"
#140000
1"
11
10
#160000
0"
#180000
1"
1O
1L
1K
06
1?
1<
1;
01
00
0;
#200000
0"
#220000
1"
10
12
0C
#240000
0"
#260000
1"
0K
16
05
1;
00
02
1@
0?
0;
1C
#280000
0"
#300000
1"
11
13
1H
0G
#320000
0"
#340000
1"
1P
0O
15
0@
01
03
1@
0H
1G
#360000
0"
#380000
1"
11
10
13
12
14
1H
0G
0C
#400000
0"
#420000
1"
18
1-
01
00
03
02
04
0H
1G
1C
#440000
0"
#460000
1"
11
10
#480000
0"
#500000
1"
0P
1O
1K
06
0@
1?
1;
01
00
0;
#520000
0"
#540000
1"
10
12
0C
#560000
0"
#580000
1"
0K
16
05
1;
00
02
1@
0?
0;
1C
#600000
0"
#620000
1"
11
13
1H
0G
#640000
0"
#660000
1"
1P
0O
15
0@
01
03
1@
0H
1G
#680000
0"
#700000
1"
11
10
13
12
14
1H
0G
0C
#720000
0"
#740000
1"
01
00
03
02
04
0H
1G
1C
#760000
0"
#780000
1"
11
10
#800000
0"
#820000
1"
0P
1O
1K
06
0@
1?
1;
01
00
0;
#840000
0"
#860000
1"
10
12
0C
#880000
0"
#900000
1"
0K
16
05
1;
00
02
1@
0?
0;
1C
#920000
0"
#940000
1"
11
13
1H
0G
#960000
0"
#980000
1"
1P
0O
15
0@
01
03
1@
0H
1G
#1000000
0"
#1020000
1"
11
10
13
12
14
1H
0G
0C
#1040000
0"
#1060000
1"
01
00
03
02
04
0H
1G
1C
#1080000
0"
#1100000
1"
11
10
#1120000
0"
#1140000
1"
0P
1O
1K
06
0@
1?
1;
01
00
0;
#1160000
0"
#1180000
1"
10
12
0C
#1200000
0"
#1220000
1"
0K
16
05
1;
00
02
1@
0?
0;
1C
#1240000
0"
#1260000
1"
11
13
1H
0G
#1280000
0"
#1300000
1"
1P
0O
15
0@
01
03
1@
0H
1G
#1320000
1+
1*
1)
0(
1&
1#
0"
1J
1I
1H
0G
1E
#1340000
1"
11
10
13
12
14
0J
0I
0E
0C
#1360000
0#
0"
#1380000
1"
01
00
03
02
04
1J
1I
1E
1C
#1400000
0"
#1420000
1"
11
10
#1440000
0"
#1460000
1"
1R
1Q
1M
1K
06
1B
1A
1=
1;
01
00
1>
0;
#1480000
0"
#1500000
1"
10
12
1F
0C
#1520000
0"
#1540000
1"
1N
0K
16
0>
0=
0<
00
02
1>
1=
1<
0F
1C
#1560000
0"
#1580000
1"
11
10
13
12
14
1F
0C
#1600000
0"
#1620000
1"
1:
19
1/
1.
01
00
03
02
04
0F
1C
#1640000
0"
#1660000
1"
11
10
#1680000
0"
#1700000
1"
0N
1K
06
0>
1;
01
00
1>
0;
#1720000
0"
#1740000
1"
10
12
1F
0C
#1760000
0"
#1780000
1"
1N
0K
16
0>
0=
0<
00
02
1>
1=
1<
0F
1C
#1800000
0"
#1820000
1"
11
10
13
12
14
1F
0C
#1840000
0"
#1860000
1"
01
00
03
02
04
0F
1C
#1880000
0"
#1900000
1"
11
10
#1920000
0"
#1940000
1"
0N
1K
06
0>
1;
01
00
1>
0;
#1960000
0"
#1980000
1"
10
12
1F
0C
#2000000
0"
#2020000
1"
1N
0K
16
0>
0=
0<
00
02
1>
1=
1<
0F
1C
#2040000
0"
#2060000
1"
11
10
13
12
14
1F
0C
#2080000
0"
#2100000
1"
01
00
03
02
04
0F
1C
#2120000
0"
#2140000
1"
11
10
#2160000
0"
#2180000
1"
0N
1K
06
0>
1;
01
00
1>
0;
#2200000
0"
#2220000
1"
10
12
1F
0C
#2240000
0"
#2260000
1"
1N
0K
16
0>
0=
0<
00
02
1>
1=
1<
0F
1C
#2280000
0"
#2300000
1"
11
10
13
12
14
1F
0C
#2320000
0"
#2340000
1"
01
00
03
02
04
0F
1C
#2360000
0"
#2380000
1"
11
10
#2400000
0"
#2420000
1"
0N
1K
06
0>
1;
01
00
1>
0;
#2440000
0"
#2460000
1"
10
12
1F
0C
#2480000
0"
#2500000
1"
1N
0K
16
0>
0=
0<
00
02
1>
1=
1<
0F
1C
#2520000
0"
#2540000
1"
11
10
13
12
14
1F
0C
#2560000
0*
1(
1'
1#
0"
#2580000
1"
01
00
03
02
04
0I
1G
1C
#2600000
0#
0"
#2620000
1"
11
10
#2640000
0"
#2660000
1"
0Q
1O
1K
06
0A
1?
1;
01
00
0>
0<
0;
#2680000
0"
#2700000
1"
10
12
0F
0D
0C
#2720000
0"
#2740000
1"
0N
0L
0K
16
05
1>
0=
1<
00
02
1A
0@
0>
1=
0<
1F
1D
1C
#2760000
0"
#2780000
1"
11
13
1I
0H
#2800000
0"
#2820000
1"
1Q
0P
0A
01
03
0I
1H
#2840000
0"
#2860000
1"
11
13
0H
#2880000
0"
#2900000
1"
0Q
1A
1@
0?
01
03
1H
#2920000
0"
#2940000
1"
11
13
1I
0G
#2960000
0"
#2980000
1"
1Q
1P
0O
0A
01
03
0I
1G
#3000000
0"
#3020000
1"
11
13
0G
#3040000
0"
#3060000
1"
0Q
1A
0@
01
03
1G
#3080000
0"
#3100000
1"
11
13
1I
0H
0G
#3120000
0"
#3140000
1"
1Q
0P
0A
01
03
0I
1H
1G
#3160000
0"
#3180000
1"
11
13
0H
0G
#3200000
0"
#3220000
1"
0Q
06
15
1A
1@
1?
01
03
0A
0@
0?
1>
0=
1H
1G
#3240000
0"
#3260000
1"
10
12
0E
0D
0C
#3280000
0"
#3300000
1"
1N
0M
16
0>
00
02
1>
1E
1D
1C
#3320000
0"
#3340000
1"
11
10
13
12
14
0H
0G
0E
0D
0C
#3360000
0"
#3380000
1"
09
08
0.
0-
01
00
03
02
04
1H
1G
1E
1D
1C
#3400000
0"
#3420000
1"
11
10
#3440000
0"
#3460000
1"
1P
1O
1M
1L
1K
06
1@
1?
1=
1<
1;
01
00
0>
0<
0;
#3480000
0"
#3500000
1"
10
12
0F
0D
0C
#3520000
0"
#3540000
1"
0N
0L
0K
16
05
1>
0=
1<
00
02
1A
0@
0>
1=
0<
1F
1D
1C
#3560000
0"
#3580000
1"
11
13
1I
0H
#3600000
0"
#3620000
1"
1Q
0P
0A
01
03
0I
1H
#3640000
0"
#3660000
1"
11
13
0H
#3680000
0"
#3700000
1"
0Q
1A
1@
0?
01
03
1H
#3720000
0"
#3740000
1"
11
13
1I
0G
#3760000
0"
#3780000
1"
1Q
1P
0O
0A
01
03
0I
1G
#3800000
1*
0)
0(
0%
1#
0"
1I
0H
0G
0D
#3820000
1"
11
13
0I
1H
#3840000
0#
0"
#3860000
1"
0Q
1A
0@
01
03
1I
0H
#3880000
0"
#3900000
1"
11
13
#3920000
0"
#3940000
1"
1Q
0P
0A
01
03
#3960000
0"
#3980000
1"
11
13
0I
#4000000
0"
#4020000
1"
0Q
06
15
1A
1@
1?
01
03
0A
0@
0?
1>
0=
1I
#4040000
0"
#4060000
1"
10
12
0E
0C
#4080000
0"
#4100000
1"
1N
0M
16
0>
00
02
1>
1E
1C
#4120000
0"
#4140000
1"
11
10
13
12
14
0I
0E
0C
#4160000
0"
#4180000
1"
01
00
03
02
04
1I
1E
1C
#4200000
0"
#4220000
1"
11
10
#4240000
0"
#4260000
1"
1Q
1M
1K
06
1A
1=
1;
01
00
0>
0=
#4280000
0"
#4300000
1"
10
12
0F
0E
#4320000
0"
#4340000
1"
0N
0M
1>
1<
0;
00
02
1F
1E
#4360000
0"
#4380000
1"
10
12
0E
1D
0C
#4400000
0"
#4420000
1"
1N
1L
0K
0>
1=
0<
00
02
1E
0D
1C
#4440000
0"
#4460000
1"
10
12
0F
0C
#4480000
0"
#4500000
1"
0N
1M
0L
16
05
1>
1<
1;
00
02
0A
0>
0<
0;
1F
1C
#4520000
0"
#4540000
1"
11
13
0I
#4560000
0"
#4580000
1"
0Q
06
15
1A
1@
1?
01
03
0A
0@
0?
1>
0=
1I
#4600000
0"
#4620000
1"
10
12
0E
0C
#4640000
0"
#4660000
1"
1N
0M
16
0>
00
02
1>
1E
1C
#4680000
0"
#4700000
1"
11
10
13
12
14
0I
0E
0C
#4720000
0"
#4740000
1"
01
00
03
02
04
1I
1E
1C
#4760000
0"
#4780000
1"
11
10
#4800000
0"
#4820000
1"
1Q
1M
1K
06
1A
1=
1;
01
00
0>
0=
#4840000
0"
#4860000
1"
10
12
0F
0E
#4880000
0"
#4900000
1"
0N
0M
1>
1<
0;
00
02
1F
1E
#4920000
0"
#4940000
1"
10
12
0E
1D
0C
#4960000
0"
#4980000
1"
1N
1L
0K
0>
1=
0<
00
02
1E
0D
1C
#5000000
0"
#5020000
1"
10
12
0F
0C
#5040000
1)
1(
0&
1%
0$
1#
0"
1H
1G
#5060000
1"
0N
1M
0L
16
05
1>
1<
1;
00
02
0A
0>
0<
0;
1F
0E
1D
#5080000
0#
0"
#5100000
1"
11
13
0I
0H
0G
#5120000
0"
#5140000
1"
0Q
06
15
1A
1@
1?
01
03
0A
0@
0?
1>
0=
1I
1H
1G
#5160000
0"
#5180000
1"
10
12
0D
#5200000
0"
#5220000
1"
1N
0M
16
0>
00
02
1>
1D
#5240000
0"
#5260000
1"
11
10
13
12
14
0I
0H
0G
0D
#5280000
0"
#5300000
1"
01
00
03
02
04
1I
1H
1G
1D
#5320000
0"
#5340000
1"
11
10
#5360000
0"
#5380000
1"
1Q
1P
1O
1L
05
1A
1@
1?
1<
01
00
0B
0@
#5400000
0"
#5420000
1"
11
13
0J
0H
#5440000
0"
#5460000
1"
0R
0P
1B
0A
1@
0?
01
03
1J
1H
#5480000
0"
#5500000
1"
11
13
0I
0G
#5520000
0"
#5540000
1"
1R
0Q
1P
0O
15
0B
0@
01
03
1B
1@
1I
1G
#5560000
0"
#5580000
1"
11
10
13
12
14
0I
0G
#5600000
0"
#5620000
1"
18
1-
01
00
03
02
04
1I
1G
#5640000
0"
#5660000
1"
11
10
#5680000
0"
#5700000
1"
1Q
1O
05
1A
1?
01
00
0B
0@
#5720000
0"
#5740000
1"
11
13
0J
0H
#5760000
0"
#5780000
1"
0R
0P
1B
0A
1@
0?
01
03
1J
1H
#5800000
0"
#5820000
1"
11
13
0I
0G
#5840000
0"
#5860000
1"
1R
0Q
1P
0O
15
0B
0@
01
03
1B
1@
1I
1G
#5880000
0"
#5900000
1"
11
10
13
12
14
0I
0G
#5920000
0"
#5940000
1"
01
00
03
02
04
1I
1G
#5960000
0"
#5980000
1"
11
10
#6000000
0"
#6020000
1"
1Q
1O
05
1A
1?
01
00
0B
0@
#6040000
0"
#6060000
1"
11
13
0J
0H
#6080000
0"
#6100000
1"
0R
0P
1B
0A
1@
0?
01
03
1J
1H
#6120000
0"
#6140000
1"
11
13
0I
0G
#6160000
0"
#6180000
1"
1R
0Q
1P
0O
15
0B
0@
01
03
1B
1@
1I
1G
#6200000
0"
#6220000
1"
11
10
13
12
14
0I
0G
#6240000
0"
#6260000
1"
01
00
03
02
04
1I
1G
#6280000
0+
0(
0'
1&
1#
0"
0J
0G
0F
1E
#6300000
1"
11
10
#6320000
0#
0"
#6340000
1"
0R
1Q
0N
1M
0B
1A
0>
1=
01
00
#6360000
0"
#6380000
1"
11
10
13
12
14
#6400000
0"
#6420000
1"
0:
19
0/
1.
01
00
03
02
04
#6440000
0"
#6460000
1"
11
10
#6480000
0"
#6500000
1"
01
00
#6520000
0"
#6540000
1"
11
10
13
12
14
#6560000
0"
#6580000
1"
01
00
03
02
04
#6600000
0"
#6620000
1"
11
10
#6640000
0"
#6660000
1"
01
00
#6680000
0"
#6700000
1"
11
10
13
12
14
#6720000
0"
#6740000
1"
01
00
03
02
04
#6760000
0"
#6780000
1"
11
10
#6800000
0"
#6820000
1"
01
00
#6840000
0"
#6860000
1"
11
10
13
12
14
#6880000
0"
#6900000
1"
01
00
03
02
04
#6920000
0"
#6940000
1"
11
10
#6960000
0"
#6980000
1"
01
00
#7000000
0"
#7020000
1"
11
10
13
12
14
#7040000
0"
#7060000
1"
01
00
03
02
04
#7080000
0"
#7100000
1"
11
10
#7120000
0"
#7140000
1"
01
00
#7160000
0"
#7180000
1"
11
10
13
12
14
#7200000
0"
#7220000
1"
01
00
03
02
04
#7240000
0"
#7260000
1"
11
10
#7280000
0"
#7300000
1"
01
00
#7320000
0"
#7340000
1"
11
10
13
12
14
#7360000
0"
#7380000
1"
01
00
03
02
04
#7400000
0"
#7420000
1"
11
10
#7440000
0"
#7460000
1"
01
00
#7480000
0"
#7500000
1"
11
10
13
12
14
#7520000
1+
0&
0%
1$
1#
0"
#7540000
1"
01
00
03
02
04
1J
0E
0D
1C
#7560000
0#
0"
#7580000
1"
11
10
#7600000
0"
#7620000
1"
1R
0M
0L
1K
06
1B
0=
0<
1;
01
00
1>
0;
#7640000
0"
#7660000
1"
10
12
1F
0C
#7680000
0"
#7700000
1"
1N
0K
16
05
0>
1=
1;
00
02
0B
1>
0=
0;
0F
1C
#7720000
0"
#7740000
1"
11
13
0J
#7760000
0"
#7780000
1"
0R
1B
0A
01
03
1J
#7800000
0"
#7820000
1"
11
13
0I
#7840000
0"
#7860000
1"
1R
0Q
0B
01
03
1I
#7880000
0"
#7900000
1"
11
13
0J
0I
#7920000
0"
#7940000
1"
0R
1B
1A
0@
01
03
1J
1I
#7960000
0"
#7980000
1"
11
13
0H
#8000000
0"
#8020000
1"
1R
1Q
0P
0B
01
03
1H
#8040000
0"
#8060000
1"
11
13
0J
0H
#8080000
0"
#8100000
1"
0R
1B
0A
01
03
1J
1H
#8120000
0"
#8140000
1"
11
13
0I
0H
#8160000
0"
#8180000
1"
1R
0Q
15
0B
01
03
1B
1I
1H
#8200000
0"
#8220000
1"
11
10
13
12
14
0I
0H
1F
0C
#8240000
0"
#8260000
1"
1:
09
08
1/
0.
0-
01
00
03
02
04
1I
1H
0F
1C
#8280000
0"
#8300000
1"
11
10
#8320000
0"
#8340000
1"
1Q
1P
0N
1K
06
1A
1@
0>
1;
01
00
1>
0;
#8360000
0"
#8380000
1"
10
12
1F
0C
#8400000
0"
#8420000
1"
1N
0K
16
05
0>
1=
1;
00
02
0B
1>
0=
0;
0F
1C
#8440000
0"
#8460000
1"
11
13
0J
#8480000
0"
#8500000
1"
0R
1B
0A
01
03
1J
#8520000
0"
#8540000
1"
11
13
0I
#8560000
0"
#8580000
1"
1R
0Q
0B
01
03
1I
#8600000
0"
#8620000
1"
11
13
0J
0I
#8640000
0"
#8660000
1"
0R
1B
1A
0@
01
03
1J
1I
#8680000
0"
#8700000
1"
11
13
0H
#8720000
0"
#8740000
1"
1R
1Q
0P
0B
01
03
1H
#8760000
0+
0)
1'
1&
1%
1#
0"
0J
0H
1F
1E
1D
#8780000
1"
11
13
#8800000
0#
0"
#8820000
1"
0R
1B
0A
01
03
#8840000
0"
#8860000
1"
11
13
1J
0I
#8880000
0"
#8900000
1"
1R
0Q
15
0B
01
03
1B
0J
1I
#8920000
0"
#8940000
1"
11
10
13
12
14
1J
0I
0E
0D
0C
#8960000
0"
#8980000
1"
01
00
03
02
04
0J
1I
1E
1D
1C
#9000000
0"
#9020000
1"
11
10
#9040000
0"
#9060000
1"
0R
1Q
1M
1L
1K
06
0B
1A
1=
1<
1;
01
00
0=
#9080000
0"
#9100000
1"
10
12
0E
#9120000
0"
#9140000
1"
0M
1=
0<
00
02
1E
#9160000
0"
#9180000
1"
10
12
0D
#9200000
0"
#9220000
1"
1M
0L
0=
00
02
1D
#9240000
0"
#9260000
1"
10
12
0E
0D
#9280000
0"
#9300000
1"
0M
1=
1<
0;
00
02
1E
1D
#9320000
0"
#9340000
1"
10
12
0C
#9360000
0"
#9380000
1"
1M
1L
0K
0=
00
02
1C
#9400000
0"
#9420000
1"
10
12
0E
0C
#9440000
0"
#9460000
1"
0M
1=
0<
00
02
1E
1C
#9480000
0"
#9500000
1"
10
12
0D
0C
#9520000
0"
#9540000
1"
1M
0L
0=
00
02
1D
1C
#9560000
0"
#9580000
1"
10
12
0E
0D
0C
#9600000
0"
#9620000
1"
0M
16
05
1=
1<
1;
00
02
1B
0A
0=
0<
0;
1E
1D
1C
#9640000
0"
#9660000
1"
11
13
1J
0I
#9680000
0"
#9700000
1"
1R
0Q
15
0B
01
03
1B
0J
1I
#9720000
0"
#9740000
1"
11
10
13
12
14
1J
0I
0E
0D
0C
#9760000
0"
#9780000
1"
01
00
03
02
04
0J
1I
1E
1D
1C
#9800000
0"
#9820000
1"
11
10
#9840000
0"
#9860000
1"
0R
1Q
1M
1L
1K
06
0B
1A
1=
1<
1;
01
00
0=
#9880000
0"
#9900000
1"
10
12
0E
#9920000
0"
#9940000
1"
0M
1=
0<
00
02
1E
#9960000
0"
#9980000
1"
10
12
0D
